pyparti/__init__.py
pyparti/align_archetypes/__init__.py
pyparti/align_archetypes/cluster_vertices.py
pyparti/align_archetypes/interpret_clusters.py
pyparti/dat/genes_affected_by_dissociation_and_processing_time.csv
pyparti/dat/protein_coding_genes_list.csv
pyparti/fit_polytope/__init__.py
pyparti/fit_polytope/calculate_hull_volume.py
pyparti/fit_polytope/filter_fits.py
pyparti/fit_polytope/find_min_polytope.py
pyparti/fit_polytope/fit_polytope.py
pyparti/fit_polytope/significance.py
pyparti/get_genes/__init__.py
pyparti/get_genes/get_genes.py
pyparti/get_genes/set_top_cells.py
pyparti/plot/__init__.py
pyparti/plot/contents.py
pyparti/plot/expression.py
pyparti/plot/gene_frequencies.py
pyparti/plot/p_value.py
pyparti/preprocess/__init__.py
pyparti/preprocess/preprocess.py
pyparti/preprocess/utils.py
pyparti-0.0.1a0.dist-info/licenses/LICENSE
pyparti-0.0.1a0.dist-info/METADATA
pyparti-0.0.1a0.dist-info/WHEEL
pyparti-0.0.1a0.dist-info/top_level.txt
pyparti-0.0.1a0.dist-info/RECORD
